setup.py
brynq_sdk_zoho/__init__.py
brynq_sdk_zoho/extract_zoho_desk.py
brynq_sdk_zoho/upload_zoho_desk.py
brynq_sdk_zoho.egg-info/PKG-INFO
brynq_sdk_zoho.egg-info/SOURCES.txt
brynq_sdk_zoho.egg-info/dependency_links.txt
brynq_sdk_zoho.egg-info/not-zip-safe
brynq_sdk_zoho.egg-info/requires.txt
brynq_sdk_zoho.egg-info/top_level.txt