Metadata-Version: 1.0
Name: brynq-sdk-zoho
Version: 2.0.4
Summary: ZOHO wrapper from BrynQ
Home-page: UNKNOWN
Author: BrynQ
Author-email: support@brynq.com
License: BrynQ License
Platform: UNKNOWN
